cryptoforecast_io_scraper/__init__.py
cryptoforecast_io_scraper/exceptions.py
cryptoforecast_io_scraper/request.py
cryptoforecast_io_scraper/test_dataReq.py
cryptoforecast_io_scraper-0.1.0.dist-info/LICENSE
cryptoforecast_io_scraper-0.1.0.dist-info/METADATA
cryptoforecast_io_scraper-0.1.0.dist-info/WHEEL
cryptoforecast_io_scraper-0.1.0.dist-info/top_level.txt
cryptoforecast_io_scraper-0.1.0.dist-info/RECORD
