Metadata-Version: 2.1
Name: cryptoforecast-io-scraper
Version: 0.1.0
Summary: Simplified Pseudo API for CryptoForecast.io
Home-page: https://github.com/seekersoftec/cryptoforecast_io_scraper/
Author: ['Seekersoftec']
Author-email: seekersoftec@gmail.com
License: Apache 2.0
Keywords: cryptoforecast.io scraper
Platform: UNKNOWN
Classifier: Development Status :: 4 - Beta
Classifier: Intended Audience :: Developers
Classifier: Programming Language :: Python :: 3.3
Classifier: Programming Language :: Python :: 3.4
Classifier: Programming Language :: Python :: 3.5
Classifier: Programming Language :: Python :: 3.6
Classifier: Programming Language :: Python :: 3.7
Classifier: License :: OSI Approved :: MIT License
Requires-Dist: requests
